odoo9_addon_auth_totp_password_security-9.0.1.0.0-py2.7-nspkg.pth
odoo9_addon_auth_totp_password_security-9.0.1.0.0.dist-info/DESCRIPTION.rst
odoo9_addon_auth_totp_password_security-9.0.1.0.0.dist-info/METADATA
odoo9_addon_auth_totp_password_security-9.0.1.0.0.dist-info/RECORD
odoo9_addon_auth_totp_password_security-9.0.1.0.0.dist-info/WHEEL
odoo9_addon_auth_totp_password_security-9.0.1.0.0.dist-info/metadata.json
odoo9_addon_auth_totp_password_security-9.0.1.0.0.dist-info/namespace_packages.txt
odoo9_addon_auth_totp_password_security-9.0.1.0.0.dist-info/top_level.txt
odoo_addons/auth_totp_password_security/README.rst
odoo_addons/auth_totp_password_security/__init__.py
odoo_addons/auth_totp_password_security/__openerp__.py
odoo_addons/auth_totp_password_security/controllers/__init__.py
odoo_addons/auth_totp_password_security/controllers/main.py
odoo_addons/auth_totp_password_security/tests/__init__.py
odoo_addons/auth_totp_password_security/tests/test_main.py
