Metadata-Version: 2.0
Name: odoo9-addon-auth-totp-password-security
Version: 9.0.1.0.0
Summary: auth_totp and password_security compatibility
Home-page: https://github.com/OCA/server-tools
Author: LasLabs, Odoo Community Association (OCA)
Author-email: support@odoo-community.org
License: LGPL-3
Platform: UNKNOWN
Classifier: Programming Language :: Python
Classifier: Framework :: Odoo
Classifier: License :: OSI Approved :: GNU Lesser General Public License v3 (LGPLv3)
Requires-Python: ~=2.7
Requires-Dist: odoo (<9.1a,>=9.0a)
Requires-Dist: odoo9-addon-auth-totp
Requires-Dist: odoo9-addon-password-security
